odoo10_addon_l10n_ch_states-10.0.1.0.0-py2.7-nspkg.pth
odoo/addons/l10n_ch_states/__manifest__.py
odoo/addons/l10n_ch_states/__init__.py
odoo/addons/l10n_ch_states/README.rst
odoo/addons/l10n_ch_states/models/__init__.py
odoo/addons/l10n_ch_states/models/res_country.py
odoo/addons/l10n_ch_states/i18n/nb_NO.po
odoo/addons/l10n_ch_states/i18n/it.po
odoo/addons/l10n_ch_states/i18n/l10n_ch_states.pot
odoo/addons/l10n_ch_states/i18n/de.po
odoo/addons/l10n_ch_states/i18n/fr.po
odoo/addons/l10n_ch_states/data/res_country_states.xml
odoo10_addon_l10n_ch_states-10.0.1.0.0.dist-info/top_level.txt
odoo10_addon_l10n_ch_states-10.0.1.0.0.dist-info/WHEEL
odoo10_addon_l10n_ch_states-10.0.1.0.0.dist-info/RECORD
odoo10_addon_l10n_ch_states-10.0.1.0.0.dist-info/metadata.json
odoo10_addon_l10n_ch_states-10.0.1.0.0.dist-info/DESCRIPTION.rst
odoo10_addon_l10n_ch_states-10.0.1.0.0.dist-info/METADATA
odoo10_addon_l10n_ch_states-10.0.1.0.0.dist-info/namespace_packages.txt
